[
  {
    "intersection_id": "UNKNOWN",
    "camera_id": "UNKNOWN",
    "signal_group": "D",
    "vertices": [
      [
        2248,
        409
      ],
      [
        1826,
        424
      ],
      [
        1459,
        154
      ],
      [
        1652,
        152
      ]
    ]
  },
  {
    "intersection_id": "UNKNOWN",
    "camera_id": "UNKNOWN",
    "signal_group": "B",
    "vertices": [
      [
        1238,
        441
      ],
      [
        1821,
        423
      ],
      [
        1483,
        158
      ],
      [
        1235,
        150
      ]
    ]
  },
  {
    "intersection_id": "UNKNOWN",
    "camera_id": "UNKNOWN",
    "signal_group": "H",
    "vertices": [
      [
        1362,
        147
      ],
      [
        1562,
        432
      ],
      [
        1236,
        440
      ],
      [
        1233,
        148
      ]
    ]
  }
]
